Metadata-Version: 2.4
Name: adafruit-circuitpython-tfmini
Version: 1.2.23
Summary: A CircuitPython/Python library for Benewake`s TF mini distance sensor
Author-email: Adafruit Industries <circuitpython@adafruit.com>
License: MIT
Project-URL: Homepage, https://github.com/adafruit/Adafruit_CircuitPython_TFmini
Keywords: adafruit,tfmini,benewake,distance,sensor,hardware,micropython,circuitpython
Classifier: Intended Audience :: Developers
Classifier: Topic :: Software Development :: Libraries
Classifier: Topic :: Software Development :: Embedded Systems
Classifier: Topic :: System :: Hardware
Classifier: License :: OSI Approved :: MIT License
Classifier: Programming Language :: Python :: 3
License-File: LICENSE
Requires-Dist: Adafruit-Blinka
Requires-Dist: pyserial
Requires-Dist: adafruit-circuitpython-typing
Requires-Dist: typing-extensions~=4.0
Provides-Extra: optional
Dynamic: license-file
